cxupdater/__init__.py
cxupdater/config.py
cxupdater/pipe_connecter.py
cxupdater/update_finder.py
cxupdater/utils.py
cxupdater/version_parser.py
cxupdater/commands/__init__.py
cxupdater/commands/build_update.py
cxupdater/scripts/__init__.py
cxupdater/scripts/generate_toml.py
cxupdater/scripts/run_app.py
cxupdater/scripts/update_installer.py
cxupdater-0.3.6.dist-info/METADATA
cxupdater-0.3.6.dist-info/WHEEL
cxupdater-0.3.6.dist-info/entry_points.txt
cxupdater-0.3.6.dist-info/licenses/LICENSE
cxupdater-0.3.6.dist-info/RECORD
