Metadata-Version: 2.4
Name: cxupdater
Version: 0.3.6
Summary: Auto-update an application on Python
Project-URL: Homepage, https://github.com/oleg-sung/cxupdater
Project-URL: Issues, https://github.com/oleg-sung/cxupdater/issues
Author-email: Oleg Sungurovsky <safasgasc.asfg@gmail.com>
License:                                  Apache License
License-File: LICENSE
Classifier: License :: OSI Approved :: MIT License
Classifier: Operating System :: OS Independent
Classifier: Programming Language :: Python :: 3
Classifier: Programming Language :: Python :: 3.7
Classifier: Programming Language :: Python :: 3.8
Classifier: Programming Language :: Python :: 3.9
Requires-Python: >=3.9
Requires-Dist: cx-freeze>=7.2.9
Requires-Dist: packaging>=24.2
Requires-Dist: pywin32>=308
Requires-Dist: requests>=2.32.3
Requires-Dist: toml>=0.10.2
